revERNIEBot/__init__.py
revERNIEBot/selenium/__init__.py
reverniebot-0.0.7.dist-info/METADATA
reverniebot-0.0.7.dist-info/WHEEL
reverniebot-0.0.7.dist-info/licenses/LICENSE
reverniebot-0.0.7.dist-info/RECORD
